net2i/__init__.py
net2i/net2i.py
net2i-2.6.dist-info/licenses/LICENSE
net2i-2.6.dist-info/METADATA
net2i-2.6.dist-info/WHEEL
net2i-2.6.dist-info/top_level.txt
net2i-2.6.dist-info/RECORD
