Metadata-Version: 2.4
Name: net2i
Version: 2.6
Summary: NeT2i (Network to Image) converts network traffic data into RGB images suitable for CNN-based anomaly detection.
Author-email: Omesh Fernando <omeshf@gmail.com>
License-Expression: MIT
Project-URL: Homepage, https://github.com/omeshF/NeT2I
Project-URL: Issues, https://github.com/omeshF/NeT2I/issues
Project-URL: Documentation, https://github.com/omeshF/NeT2I#readme
Classifier: Programming Language :: Python :: 3
Classifier: Operating System :: OS Independent
Classifier: Topic :: Security
Classifier: Topic :: Scientific/Engineering :: Artificial Intelligence
Classifier: Intended Audience :: Science/Research
Classifier: Intended Audience :: Developers
Classifier: Development Status :: 4 - Beta
Requires-Python: >=3.9
License-File: LICENSE
Dynamic: license-file
